[
    {
        "Orderid" : 1,
        "Name" : "raisa",
        "Restaurant" : "Moonshine Grill",
        "Date" : "2018-06-25",
        "Paymentmethod" : "Wallet-paid",
        "Processstatus": "Pending",
        "Totalamount":44.54,
        "Commission": 3.24
    },
    {
        "Orderid" : 2,
        "Name" : "jhon",
        "Restaurant" : "Moonshine Grill",
        "Date" : "2018-06-27",
        "Paymentmethod" : "Wallet-paid",
        "Processstatus": "Pending",
        "Totalamount":50,
        "Commission": 4
    }



]